README.md
setup.py
l298n/__init__.py
l298n/l298n.py
l298n.egg-info/PKG-INFO
l298n.egg-info/SOURCES.txt
l298n.egg-info/dependency_links.txt
l298n.egg-info/top_level.txt