Metadata-Version: 2.1
Name: l298n
Version: 0.0.1
Summary: A module to assist in controlling an L298N H-Bridge motor driver.
Home-page: https://github.com/Psuedohim/l298n
Author: Psuedohim
Author-email: 8im8yhq1zatd@opayq.com
License: UNKNOWN
Platform: UNKNOWN
Classifier: Programming Language :: Python :: 3
Classifier: License :: OSI Approved :: MIT License
Classifier: Operating System :: OS Independent
